pymyip.py
setup.cfg
setup.py
pymyip0.egg-info/PKG-INFO
pymyip0.egg-info/SOURCES.txt
pymyip0.egg-info/dependency_links.txt
pymyip0.egg-info/not-zip-safe
pymyip0.egg-info/top_level.txt