Metadata-Version: 1.0
Name: pymyip0
Version: 0.1
Summary: Module for python 3.x to find out your ip, city, country.
